PyTestAI/__init__.py
PyTestAI/cli.py
PyTestAI/decorators.py
PyTestAI/generator.py
PyTestAI/utils.py
pytestai_generator-2.0.1.dist-info/LICENSE
pytestai_generator-2.0.1.dist-info/METADATA
pytestai_generator-2.0.1.dist-info/WHEEL
pytestai_generator-2.0.1.dist-info/entry_points.txt
pytestai_generator-2.0.1.dist-info/top_level.txt
pytestai_generator-2.0.1.dist-info/RECORD
