Metadata-Version: 2.2
Name: PyTestAI-Generator
Version: 2.0.1
Summary: A CLI tool to generate pytest test cases using AI.
Home-page: https://github.com/PinsaraPerera/PyTestAI
Author: Pawan Pinsara
Author-email: 1pawanpinsara@gmail.com
License: MIT
Classifier: Programming Language :: Python :: 3
Classifier: License :: OSI Approved :: MIT License
Classifier: Operating System :: OS Independent
Classifier: Topic :: Software Development :: Testing
Classifier: Intended Audience :: Developers
Requires-Python: >=3.8
License-File: LICENSE
Requires-Dist: requests<2.32.3,>=2.25.1
Requires-Dist: colorama<0.5.0,>=0.4.6
Requires-Dist: tqdm<4.67.1,>=4.62.1
Requires-Dist: pytest<8.4.4,>=8.1.1
Dynamic: author
Dynamic: author-email
Dynamic: classifier
Dynamic: description
Dynamic: description-content-type
Dynamic: home-page
Dynamic: license
Dynamic: requires-dist
Dynamic: requires-python
Dynamic: summary
